telegramify_markdown-0.5.4.dist-info/METADATA
telegramify_markdown-0.5.4.dist-info/WHEEL
telegramify_markdown-0.5.4.dist-info/entry_points.txt
telegramify_markdown-0.5.4.dist-info/licenses/LICENSE
telegramify_markdown/__init__.py
telegramify_markdown/customize.py
telegramify_markdown/interpreters.py
telegramify_markdown/latex_escape/__init__.py
telegramify_markdown/latex_escape/const.py
telegramify_markdown/latex_escape/helper.py
telegramify_markdown/logger.py
telegramify_markdown/markdown.py
telegramify_markdown/mermaid.py
telegramify_markdown/mime.py
telegramify_markdown/render.py
telegramify_markdown/type.py
telegramify_markdown/word_count.py
telegramify_markdown-0.5.4.dist-info/RECORD
