Metadata-Version: 2.1
Name: telegramify-markdown
Version: 0.5.4
Summary: Makes it easy to send Markdown in Telegram MarkdownV2 style
Author-Email: sudoskys <coldlando@hotmail.com>
License: MIT
Project-URL: repository, https://github.com/sudoskys/telegramify-markdown
Requires-Python: >=3.9
Requires-Dist: mistletoe==1.4.0
Provides-Extra: mermaid
Requires-Dist: Pillow>=10.4.0; extra == "mermaid"
Requires-Dist: aiohttp>=3.10.11; extra == "mermaid"
Provides-Extra: tests
Requires-Dist: pytest<6; extra == "tests"
Requires-Dist: pytelegrambotapi>=4.22.0; extra == "tests"
Requires-Dist: python-dotenv>=1.0.1; extra == "tests"
Requires-Dist: mock<4,>=1.0.1; python_version < "3.4" and extra == "tests"
